[
  {
    "feature": {
      "title": "帳號服務",
      "description": "該功能提供對教職員、學生及校友(畢業五年內)的帳號管理服務。使用者需使用電算中心的帳號進行登錄，以存取相應的服務。"
    }
  },
  {
    "feature": {
      "title": "NCU Mail",
      "description": "NCU Mail 是一個郵件服務平台，使用者可以在此讀取來自 NCU Webmail 的郵件。該平台提供了方便的介面，使用者可以輕鬆管理和查閱自己的郵件。"
    }
  },
  {
    "feature": {
      "title": "字體大小調整",
      "description": "該功能允許使用者調整網站的字體大小，以改善可讀性。使用者可以選擇小、中或大三種字體大小，以適應個人的閱讀習慣。"
    }
  },
  {
    "feature": {
      "title": "JavaScript 功能提示",
      "description": "系統提示若使用者的瀏覽器不支援JavaScript功能，可能會導致網頁某些功能無法正常使用。建議使用者開啟瀏覽器的 JavaScript 狀態，以獲得最佳的使用體驗。"
    }
  },
  {
    "feature": {
      "title": "服務公告及文件",
      "description": "使用者可以查閱 NCU Mail Support 相關的服務公告及文件，以獲得最新的資訊和支援。這些公告將幫助使用者理解平台的變動及新的功能。"
    }
  }
]